ez_setup.py
pushroulette.py
setup.py
pushroulette.egg-info/PKG-INFO
pushroulette.egg-info/SOURCES.txt
pushroulette.egg-info/dependency_links.txt
pushroulette.egg-info/requires.txt
pushroulette.egg-info/top_level.txt