Metadata-Version: 1.0
Name: pushroulette
Version: 1.1
Summary: Plays a random 5 second clip from soundcloud for every git push
Home-page: https://github.com/Astonish-Results/push-roulette
Author: Matt Carrier
Author-email: mcarrieruri@gmail.com
License: UNKNOWN
Platform: UNKNOWN
